{"version":1,"resource":"file:///home/user/.config/hypr/hyprland.conf","entries":[{"id":"KMbY.conf","timestamp":1705883439305},{"id":"Yi7W.conf","timestamp":1705883453185},{"id":"w4Gb.conf","source":"undoRedo.source","timestamp":1705883454408},{"id":"Kns1.conf","timestamp":1705883494438},{"id":"wfOt.conf","timestamp":1705883580503},{"id":"ECV7.conf","timestamp":1705883666074},{"id":"DAaw.conf","timestamp":1705883692102},{"id":"cprT.conf","timestamp":1705883744604},{"id":"nFq6.conf","timestamp":1705883760496},{"id":"hgPF.conf","timestamp":1705883785980},{"id":"VnTP.conf","timestamp":1705883875010},{"id":"QQ86.conf","timestamp":1705883933568},{"id":"W1Rc.conf","timestamp":1705883959313},{"id":"PMyQ.conf","timestamp":1705885756356},{"id":"FoqY.conf","timestamp":1705885770080},{"id":"7qga.conf","timestamp":1705887572883},{"id":"28eC.conf","timestamp":1705887793309},{"id":"pWKZ.conf","timestamp":1705945590594}]}